fxportia-0.0.1.data/scripts/portia_porter
fxportia-0.0.1.dist-info/DESCRIPTION.rst
fxportia-0.0.1.dist-info/METADATA
fxportia-0.0.1.dist-info/RECORD
fxportia-0.0.1.dist-info/WHEEL
fxportia-0.0.1.dist-info/metadata.json
fxportia-0.0.1.dist-info/top_level.txt
portia2code/__init__.py
portia2code/parser.py
portia2code/porter.py
portia2code/processors.py
portia2code/samples.py
portia2code/spiders.py
portia2code/starturls.py
portia2code/templates.py
portia2code/utils.py
