Metadata-Version: 2.0
Name: fxportia
Version: 0.0.1
Summary: Convert portia spider definitions to python scrapy spiders
Home-page: https://github.com/scrapinghub/portia2code
Author: Ruairi Fahy
Author-email: ruairi@scrapinghub.com
License: BSD
Download-URL: https://github.com/scrapinghub/portia2code/tarball/portia2code-0.0.1
Platform: Any
Classifier: Development Status :: 4 - Beta
Classifier: License :: OSI Approved :: BSD License
Classifier: Operating System :: OS Independent
Classifier: Programming Language :: Python
Classifier: Programming Language :: Python :: 2
Classifier: Programming Language :: Python :: 2.7
Requires-Dist: Scrapy
Requires-Dist: autoflake (==0.6.6)
Requires-Dist: autopep8 (==1.2.2)
Requires-Dist: dateparser
Requires-Dist: scrapely
Requires-Dist: six (==1.10.0)
Requires-Dist: slybot (>=0.13.0b20)
Requires-Dist: w3lib
